MANIFEST.in
requirements.txt
setup.cfg
setup.py
todooo/__init__.py
todooo/config.py
todooo/errors.py
todooo/list.py
todooo/repl.py
todooo/tab_complete.py
todooo/validators.py
todooo_cli.egg-info/PKG-INFO
todooo_cli.egg-info/SOURCES.txt
todooo_cli.egg-info/dependency_links.txt
todooo_cli.egg-info/entry_points.txt
todooo_cli.egg-info/requires.txt
todooo_cli.egg-info/top_level.txt