Metadata-Version: 1.1
Name: todooo-cli
Version: 1.0.5
Summary: CLI Tool for managing lists
Home-page: https://github.com/dansackett/todooo
Author: Dan Sackett
Author-email: danesackett@gmail.com
License: UNKNOWN
Platform: UNKNOWN
Classifier: Intended Audience :: Developers
Classifier: License :: OSI Approved :: MIT License
Classifier: Operating System :: Unix
Classifier: Programming Language :: Python
Classifier: Programming Language :: Python :: 2.7
